prenv/__main__.py
prenv/colorhelper.py
prenv/docker.py
prenv/download.py
prenv/enter.py
prenv/lxc.py
prenv/mount.py
prenv/process.py
prenv/rootfs.py
prenv/size.py
prenv/socket.py
prenv/tar.py
prenv/unshare.py
prenv/verbose.py
prenv/version.py
prenv/cli/cmd_create.py
prenv/cli/cmd_exec.py
prenv/cli/cmd_lxc.py
prenv/cli/cmd_run.py
prenv/cli/verbose.py
samples/test.py
tests/test_version.py
prenv-0.0.4.dist-info/LICENSE
prenv-0.0.4.dist-info/METADATA
prenv-0.0.4.dist-info/WHEEL
prenv-0.0.4.dist-info/entry_points.txt
prenv-0.0.4.dist-info/top_level.txt
prenv-0.0.4.dist-info/RECORD
