Metadata-Version: 2.1
Name: prenv
Version: 0.0.4
Summary: Portable reproducible environments for Linux applications
Home-page: https://github.com/joaompinto/prenv
Author: João Pinto
Author-email: lamego.pinto@gmail.com
License: MIT
License-File: LICENSE
Requires-Dist: drclient
Requires-Dist: print-err
Requires-Dist: requests
Requires-Dist: rich
Requires-Dist: termcolor
Requires-Dist: typer
